authorea_scripts/__init__.py
authorea_scripts/local_build.py
authorea_scripts/stripreftags.py
authorea_scripts-0.0.9.dist-info/LICENSE
authorea_scripts-0.0.9.dist-info/METADATA
authorea_scripts-0.0.9.dist-info/WHEEL
authorea_scripts-0.0.9.dist-info/entry_points.txt
authorea_scripts-0.0.9.dist-info/top_level.txt
authorea_scripts-0.0.9.dist-info/RECORD
