Metadata-Version: 2.1
Name: authorea-scripts
Version: 0.0.9
Summary: Tools for working locally with Authorea projects
Home-page: https://github.com/mpjuers/authorea-scripts
Author: Mark Juers
Author-email: mpjuers@indiana.edu
License: MIT
Platform: UNKNOWN
Classifier: Programming Language :: Python :: 3
Classifier: License :: OSI Approved :: MIT License
Classifier: Operating System :: OS Independent
Requires-Dist: pypandoc
Requires-Dist: panflute
